spacy_partial_tagger/__about__.py
spacy_partial_tagger/__init__.py
spacy_partial_tagger/collator.py
spacy_partial_tagger/pipeline.py
spacy_partial_tagger/tagger.py
spacy_partial_tagger/util.py
spacy_partial_tagger-0.15.6.dist-info/METADATA
spacy_partial_tagger-0.15.6.dist-info/WHEEL
spacy_partial_tagger-0.15.6.dist-info/entry_points.txt
spacy_partial_tagger-0.15.6.dist-info/licenses/LICENSE
spacy_partial_tagger-0.15.6.dist-info/RECORD
