Metadata-Version: 2.1
Name: spacy-partial-tagger
Version: 0.15.6
Summary: Sequence Tagger for Partially Annotated Dataset in spaCy
Project-URL: Repository, https://github.com/doccano/spacy-partial-tagger
Author-email: Yasufumi Taniguchi <yasufumi.taniguchi@gmail.com>
License: MIT License
License-File: LICENSE
Classifier: Programming Language :: Python
Classifier: Programming Language :: Python :: 3.8
Classifier: Programming Language :: Python :: 3.9
Requires-Python: <3.12,>=3.8
Requires-Dist: pytorch-partial-tagger<1.0.0,>=0.1.15
Requires-Dist: sequence-label<1.0.0,>=0.1.4
Requires-Dist: spacy-alignments<1.0.0,>=0.8.5
Requires-Dist: spacy[transformers]<4.0.0,>=3.3.1
Requires-Dist: thinc<9.0.0,>=8.0.15
Requires-Dist: torch<3.0.0,>=2.0.1
Requires-Dist: transformers[ja]<5.0.0,>=4.25.1
Provides-Extra: dev
Requires-Dist: black>=23.3.0; extra == 'dev'
Requires-Dist: flake8>=4.0.1; extra == 'dev'
Requires-Dist: isort>=5.10.1; extra == 'dev'
Requires-Dist: mypy>=1.3.1; extra == 'dev'
Requires-Dist: pytest-cov>=3.0.0; extra == 'dev'
Requires-Dist: pytest>=7.1.1; extra == 'dev'
Requires-Dist: ruff>=0.0.270; extra == 'dev'
